treeparse/__init__.py
treeparse/core/__init__.py
treeparse/core/argument.py
treeparse/core/chain.py
treeparse/core/cli.py
treeparse/core/command.py
treeparse/core/group.py
treeparse/core/option.py
treeparse/utils/color_config.py
treeparse/utils/helpers.py
treeparse-0.1.6.dist-info/METADATA
treeparse-0.1.6.dist-info/WHEEL
treeparse-0.1.6.dist-info/entry_points.txt
treeparse-0.1.6.dist-info/licenses/LICENSE
treeparse-0.1.6.dist-info/RECORD
