Metadata-Version: 2.4
Name: treeparse
Version: 0.1.6
Summary: Intuitive CLI framework using argparse, rich, and pydantic
Author: wr1
License-File: LICENSE
Requires-Python: >=3.8
Requires-Dist: pydantic<3,>=2.0.2
Requires-Dist: pyyaml<7,>=6.0
Requires-Dist: rich<14,>=13.3.1
